lau_streamlit/.DS_Store
lau_streamlit/__init__.py
lau_streamlit-1.0.0.dist-info/WHEEL
lau_streamlit-1.0.0.dist-info/METADATA
lau_streamlit-1.0.0.dist-info/RECORD
