Metadata-Version: 2.1
Name: lau-streamlit
Version: 1.0.0
Summary: 
License: Private
Author: Renato Carnauba
Author-email: contato@renatocarnauba.com.br
Requires-Python: >=3.11,<4.0
Classifier: License :: Other/Proprietary License
Classifier: Programming Language :: Python :: 3
Classifier: Programming Language :: Python :: 3.11
Requires-Dist: odmantic (>=0.9.2,<0.10.0)
Requires-Dist: ply (>=3.11,<4.0)
Requires-Dist: pydantic (>=1.10.4,<2.0.0)
Requires-Dist: python-dotenv (>=0.21.0,<0.22.0)
Requires-Dist: streamlit (>=1.17.0,<2.0.0)
Requires-Dist: streamlit-aggrid (>=0.3.3,<0.4.0)
Requires-Dist: watchdog (>=2.2.1,<3.0.0)
